CMakeLists.txt
LICENSE
MANIFEST.in
README.md
requirements.txt
setup.py
cmake/googletest.cmake
cmake/pybind11.cmake
cmake/select_compute_arch.cmake
cmake/torch.cmake
cmake/transform.cmake
cmake/Modules/FetchContent.cmake
cmake/Modules/README.md
cmake/Modules/FetchContent/CMakeLists.cmake.in
fast_rnnt/CMakeLists.txt
fast_rnnt.egg-info/PKG-INFO
fast_rnnt.egg-info/SOURCES.txt
fast_rnnt.egg-info/dependency_links.txt
fast_rnnt.egg-info/not-zip-safe
fast_rnnt.egg-info/requires.txt
fast_rnnt.egg-info/top_level.txt
fast_rnnt/csrc/CMakeLists.txt
fast_rnnt/csrc/device_guard.h
fast_rnnt/csrc/mutual_information.h
fast_rnnt/csrc/mutual_information_cpu.cu
fast_rnnt/csrc/mutual_information_cuda.cu
fast_rnnt/python/CMakeLists.txt
fast_rnnt/python/csrc/CMakeLists.txt
fast_rnnt/python/csrc/fast_rnnt.cu
fast_rnnt/python/csrc/fast_rnnt.h
fast_rnnt/python/csrc/mutual_information.cu
fast_rnnt/python/csrc/mutual_information.h
fast_rnnt/python/fast_rnnt/__init__.py
fast_rnnt/python/fast_rnnt/mutual_information.py
fast_rnnt/python/fast_rnnt/rnnt_loss.py
fast_rnnt/python/tests/CMakeLists.txt
fast_rnnt/python/tests/mutual_information_test.py
fast_rnnt/python/tests/rnnt_loss_test.py