Metadata-Version: 2.1
Name: fast-rnnt
Version: 1.3
Summary: Fast and memory-efficient RNN-T loss.
Home-page: https://github.com/danpovey/fast_rnnt
Author: Dan Povey
Author-email: dpovey@gmail.com
License: Apache licensed, as found in the LICENSE file
Classifier: Programming Language :: C++
Classifier: Programming Language :: Python
Classifier: Topic :: Scientific/Engineering :: Artificial Intelligence
License-File: LICENSE
Requires-Dist: torch>=1.5
